{
  "summary": {
    "total_files": 10534,
    "html_files": 8432,
    "js_files": 253,
    "css_files": 156,
    "json_files": 966,
    "image_files": 19,
    "other_files": 708,
    "by_directory": {
      "public": {
        "total": 1729,
        "html": 1289,
        "js": 69,
        "css": 46,
        "json": 7,
        "other": 315
      },
      "archive": {
        "total": 988,
        "html": 514,
        "js": 5,
        "css": 0,
        "json": 466,
        "other": 3
      },
      "archived-bloat": {
        "total": 42,
        "html": 7,
        "js": 2,
        "css": 2,
        "json": 2,
        "other": 29
      },
      "backup_before_css_migration": {
        "total": 2483,
        "html": 1573,
        "js": 65,
        "css": 36,
        "json": 471,
        "other": 337
      },
      "backup_before_minification": {
        "total": 35,
        "html": 0,
        "js": 0,
        "css": 35,
        "json": 0,
        "other": 0
      },
      "backups": {
        "total": 4384,
        "html": 4322,
        "js": 44,
        "css": 0,
        "json": 10,
        "other": 8
      },
      "dist": {
        "total": 873,
        "html": 727,
        "js": 68,
        "css": 37,
        "json": 10,
        "other": 16
      }
    },
    "by_type": {
      ".html": 8432,
      ".hub-backup": 10,
      ".ico": 1,
      "": 21,
      ".hub": 10,
      ".old": 1,
      ".json": 966,
      ".md": 48,
      ".js": 253,
      ".txt": 7,
      ".webmanifest": 2,
      ".master-backup": 254,
      ".css": 156,
      ".master": 229,
      ".css-polish-backup": 16,
      ".nav-backup": 20,
      ".enrich": 42,
      ".bak": 36,
      ".png": 19,
      ".sql": 5,
      ".log": 3,
      ".cache": 1,
      ".tag": 1,
      ".pdf": 1
    },
    "large_directories": []
  },
  "categories": {
    "lessons": 3155,
    "handouts": 2978,
    "games": 162,
    "units": 870,
    "assessments": 114,
    "tools": 50,
    "media": 0,
    "data": 0,
    "other": 1103
  },
  "total_html": 8432
}