{
  "original_path": "backups/css-standardize-202508111252200/public/units/y9-science-ecology/lessons/lesson-5-restoration-kaitiakitanga.html",
  "title": "Lesson 5: Restoration & Kaitiakitanga",
  "description": "Te Kete Ako - Award-winning educational platform integrating m\u0101tauranga M\u0101ori with contemporary learning",
  "cultural_level": "high",
  "subject_area": "mathematics",
  "year_level": "Not specified",
  "quality_score": 85,
  "integrated_at": "2025-10-15T09:25:46.492027",
  "integrated_by": "agent-6"
}